slidio/__init__.py
slidio/client.py
slidio/utils.py
slidio/components/__init__.py
slidio/components/graph.py
slidio/components/table.py
slidio/components/text.py
slidio-1.0.0.dist-info/METADATA
slidio-1.0.0.dist-info/WHEEL
slidio-1.0.0.dist-info/licenses/LICENSE
slidio-1.0.0.dist-info/RECORD
