Metadata-Version: 2.4
Name: slidio
Version: 1.0.0
Summary: A Python library to generate Google Slides from templates using AI-generated text and graphs
Project-URL: Homepage, https://github.com/mickaelandrieu/slidio
Project-URL: Repository, https://github.com/mickaelandrieu/slidio.git
Project-URL: Bug Tracker, https://github.com/mickaelandrieu/slidio/issues
Author-email: Mickaël Andrieu <mickael.andrieu@solvolabs.com>
License-Expression: MIT
License-File: LICENSE
Keywords: automation,google-slides,templates
Classifier: Development Status :: 4 - Beta
Classifier: Intended Audience :: Developers
Classifier: License :: OSI Approved :: MIT License
Classifier: Programming Language :: Python :: 3
Classifier: Programming Language :: Python :: 3.12
Classifier: Programming Language :: Python :: 3.13
Requires-Python: >=3.12
Requires-Dist: google-api-python-client>=2.0.0
Requires-Dist: google-auth>=2.0.0
Requires-Dist: matplotlib>=3.0.0
Provides-Extra: dev
Requires-Dist: mypy>=1.0.0; extra == 'dev'
Requires-Dist: pre-commit>=3.0.0; extra == 'dev'
Requires-Dist: pytest-cov>=4.0.0; extra == 'dev'
Requires-Dist: pytest>=7.0.0; extra == 'dev'
Requires-Dist: ruff>=0.1.0; extra == 'dev'
